octet/__init__.py
octet/base.py
octet/constants.py
octet-0.1.1.dist-info/LICENSE
octet-0.1.1.dist-info/WHEEL
octet-0.1.1.dist-info/METADATA
octet-0.1.1.dist-info/RECORD
